temporalcv/__init__.py
temporalcv/changepoint.py
temporalcv/conformal.py
temporalcv/cv.py
temporalcv/cv_financial.py
temporalcv/gates.py
temporalcv/guardrails.py
temporalcv/lag_selection.py
temporalcv/persistence.py
temporalcv/py.typed
temporalcv/regimes.py
temporalcv/stationarity.py
temporalcv/statistical_tests.py
temporalcv/bagging/__init__.py
temporalcv/bagging/base.py
temporalcv/bagging/strategies/__init__.py
temporalcv/bagging/strategies/block_bootstrap.py
temporalcv/bagging/strategies/feature_bagging.py
temporalcv/bagging/strategies/residual_bootstrap.py
temporalcv/bagging/strategies/stationary_bootstrap.py
temporalcv/benchmarks/__init__.py
temporalcv/benchmarks/base.py
temporalcv/benchmarks/fred.py
temporalcv/benchmarks/gluonts.py
temporalcv/benchmarks/m5.py
temporalcv/benchmarks/monash.py
temporalcv/compare/__init__.py
temporalcv/compare/base.py
temporalcv/compare/docs.py
temporalcv/compare/results.py
temporalcv/compare/runner.py
temporalcv/compare/adapters/__init__.py
temporalcv/compare/adapters/multi_series.py
temporalcv/compare/adapters/statsforecast_adapter.py
temporalcv/diagnostics/__init__.py
temporalcv/diagnostics/influence.py
temporalcv/diagnostics/sensitivity.py
temporalcv/inference/__init__.py
temporalcv/inference/block_bootstrap_ci.py
temporalcv/inference/wild_bootstrap.py
temporalcv/metrics/__init__.py
temporalcv/metrics/asymmetric.py
temporalcv/metrics/core.py
temporalcv/metrics/event.py
temporalcv/metrics/financial.py
temporalcv/metrics/quantile.py
temporalcv/metrics/volatility_weighted.py
temporalcv/validators/__init__.py
temporalcv/validators/theoretical.py
temporalcv-1.0.0.dist-info/METADATA
temporalcv-1.0.0.dist-info/WHEEL
temporalcv-1.0.0.dist-info/licenses/LICENSE
temporalcv-1.0.0.dist-info/RECORD
