Metadata-Version: 2.4
Name: temporalcv
Version: 1.0.0
Summary: Temporal cross-validation with leakage protection for time-series ML
Project-URL: Homepage, https://github.com/brandonmbehring-dev/temporalcv
Project-URL: Documentation, https://github.com/brandonmbehring-dev/temporalcv#readme
Project-URL: Repository, https://github.com/brandonmbehring-dev/temporalcv
Project-URL: Issues, https://github.com/brandonmbehring-dev/temporalcv/issues
Author: Brandon Behring
License-Expression: MIT
License-File: LICENSE
Keywords: cross-validation,forecasting,leakage-detection,machine-learning,temporal-validation,time-series,walk-forward
Classifier: Development Status :: 4 - Beta
Classifier: Intended Audience :: Developers
Classifier: Intended Audience :: Science/Research
Classifier: License :: OSI Approved :: MIT License
Classifier: Operating System :: OS Independent
Classifier: Programming Language :: Python :: 3
Classifier: Programming Language :: Python :: 3.9
Classifier: Programming Language :: Python :: 3.10
Classifier: Programming Language :: Python :: 3.11
Classifier: Programming Language :: Python :: 3.12
Classifier: Topic :: Scientific/Engineering
Classifier: Topic :: Scientific/Engineering :: Artificial Intelligence
Classifier: Typing :: Typed
Requires-Python: >=3.9
Requires-Dist: numpy>=1.21
Requires-Dist: scikit-learn>=1.0
Requires-Dist: scipy>=1.7
Requires-Dist: statsmodels>=0.13
Provides-Extra: all
Requires-Dist: datasetsforecast>=0.0.8; extra == 'all'
Requires-Dist: fredapi>=0.5; extra == 'all'
Requires-Dist: gluonts>=0.13; extra == 'all'
Requires-Dist: pandas>=1.3; extra == 'all'
Requires-Dist: statsforecast>=1.5; extra == 'all'
Provides-Extra: benchmarks
Requires-Dist: datasetsforecast>=0.0.8; extra == 'benchmarks'
Requires-Dist: fredapi>=0.5; extra == 'benchmarks'
Provides-Extra: changepoint
Requires-Dist: ruptures>=1.1; extra == 'changepoint'
Provides-Extra: compare
Requires-Dist: statsforecast>=1.5; extra == 'compare'
Provides-Extra: dev
Requires-Dist: hypothesis>=6.0; extra == 'dev'
Requires-Dist: mypy>=1.0; extra == 'dev'
Requires-Dist: pip-audit>=2.0; extra == 'dev'
Requires-Dist: pre-commit>=3.0; extra == 'dev'
Requires-Dist: pytest-benchmark>=4.0; extra == 'dev'
Requires-Dist: pytest-cov>=4.0; extra == 'dev'
Requires-Dist: pytest>=7.0; extra == 'dev'
Requires-Dist: ruff>=0.1.0; extra == 'dev'
Provides-Extra: docs
Requires-Dist: myst-parser>=2.0.0; extra == 'docs'
Requires-Dist: sphinx-autodoc-typehints>=1.25; extra == 'docs'
Requires-Dist: sphinx-copybutton>=0.5.2; extra == 'docs'
Requires-Dist: sphinx-rtd-theme>=2.0; extra == 'docs'
Requires-Dist: sphinx>=7.2; extra == 'docs'
Provides-Extra: fred
Requires-Dist: fredapi>=0.5; extra == 'fred'
Provides-Extra: gluonts
Requires-Dist: gluonts>=0.13; extra == 'gluonts'
Provides-Extra: monash
Requires-Dist: datasetsforecast>=0.0.8; extra == 'monash'
Provides-Extra: pandas
Requires-Dist: pandas>=1.3; extra == 'pandas'
